parsallel/VERSION
parsallel/__init__.py
parsallel/loader.py
parsallel/parser.py
parsallel/version.py
parsallel-0.0.3.dist-info/LICENSE
parsallel-0.0.3.dist-info/METADATA
parsallel-0.0.3.dist-info/WHEEL
parsallel-0.0.3.dist-info/top_level.txt
parsallel-0.0.3.dist-info/RECORD
