Metadata-Version: 2.1
Name: parsallel
Version: 0.0.3
Summary: 📚 Efficient PDF Parsing in Parallel
Home-page: https://github.com/rishiraj/parsallel
Author: Rishiraj Acharya
Author-email: heyrishiraj@gmail.com
Classifier: Programming Language :: Python :: 3
Classifier: License :: OSI Approved :: Apache Software License
Classifier: Operating System :: OS Independent
Requires-Python: >=3.9
License-File: LICENSE
Requires-Dist: PyPDF2
Requires-Dist: pymupdf
Requires-Dist: pillow
Requires-Dist: pytesseract
Requires-Dist: requests
